ytanalysis/__init__.py
ytanalysis/ytanalysis.py
ytanalysis-0.1.0.dist-info/LICENSE
ytanalysis-0.1.0.dist-info/METADATA
ytanalysis-0.1.0.dist-info/WHEEL
ytanalysis-0.1.0.dist-info/top_level.txt
ytanalysis-0.1.0.dist-info/RECORD
