Metadata-Version: 2.1
Name: ytanalysis
Version: 0.1.0
Summary: A package for analyzing YouTube channel statistics using the YouTube API
Home-page: https://github.com/dineshram0212/youtube-analysis
Author: Dinesh Ram
Author-email: dineshramdsml@gmail.com
Classifier: Programming Language :: Python :: 3
Classifier: License :: OSI Approved :: MIT License
Classifier: Operating System :: OS Independent
Requires-Python: >=3.6
License-File: LICENSE
Requires-Dist: google-api-python-client
Requires-Dist: pandas
Requires-Dist: seaborn
Requires-Dist: matplotlib
